<?xml version="1.0" encoding="utf-8"?>
<Maps>
  <Map Type="System" Name="CFS_RWY03" Priority="1" Centre="-30.320556+153.116389">
    <!--YCFS-->
    <Runway Name="03/21">
      <Threshold Name="03" Position="-30.338375+153.106547" ExtendedCentrelineTrack="220.71" ExtendedCentrelineLength="15" ExtendedCentrelineTickInterval="2" />
      <Threshold Name="21" Position="-30.324153+153.120656" />
    </Runway>
    <!--SIDs-->
    <!--STARs-->
    <Symbol Type="HollowTriangle" />
    <Symbol Type="HollowStar" />
  </Map>
  <Map Type="System" Name="CFS_RWY03_NAMES" Priority="2" Centre="-30.320556+153.116389">
    <Label>
      <Point>BANDA</Point>
      <Point>JOKER</Point>
      <Point>COOPA</Point>
      <Point>INOKE</Point>
      <Point>CORKY</Point>
      <Point>TOOKI</Point>
      <Point>WLM NDB</Point>
      <Point>LATUT</Point>
      <Point>TW VOR</Point>
      <Point>LOSKU</Point>
      <Point>UGPOT</Point>
      <Point>WONKA</Point>
      <Point>VONNI</Point>
      <Point>POSUM</Point>
      <Point>BILBY</Point>
      <Point>GALON</Point>
    </Label>
  </Map>
</Maps>