{
  "Logging": {
    "LogLevel": "Information",
    "OutputDirectory": "MaestroLogs",
    "MaxFileAgeDays": 7
  },
  "Server": {
    "Uri": "https://maestro.eoinmotherway.dev/hub",
    "Partitions": ["VATSIM", "SweatBox-1", "SweatBox-2"],
    "Permissions": {
      "ChangeTerminalConfiguration": ["Flow"],
      "ChangeLandingRates": ["Flow"],
      "MoveFlight": ["Approach", "Flow"],
      "ChangeFeederFixEstimate": ["Enroute", "Flow"],
      "ManageSlots": ["Flow"],
      "InsertOvershoot": ["Approach", "Flow"],
      "InsertDeparture": ["Flow"],
      "InsertDummy": ["Flow"],
      "MakePending": ["Enroute", "Approach", "Flow"],
      "ChangeRunway": ["Enroute", "Approach", "Flow"],
      "ManualDelay": ["Enroute", "Approach", "Flow"],
      "MakeStable": ["Enroute", "Flow"],
      "Recompute": ["Enroute", "Flow"],
      "Desequence": ["Enroute", "Approach", "Flow"],
      "Resequence": ["Flow"],
      "RemoveFlight": ["Enroute", "Approach", "Flow"]
    }
  },
  "Airports": [
    {
      "Identifier": "YSSY",
      "FeederFixes": ["RIVET", "WELSH", "BOREE", "YAKKA", "MARLN"],
      "PreferredRunways": {
        "RIVET": ["34L", "16R"],
        "WELSH": ["34R", "16L"],
        "BOREE": ["34R", "16L"],
        "YAKKA": ["34R", "16L"],
        "MARLN": ["34R", "16L"]
      },
      "Runways": [
        { 
          "Identifier": "16L",
          "Preferences": {
            "FeederFixes": ["BOREE", "YAKKA", "MARLN"]
          }
        },
        { 
          "Identifier": "34L",
          "Preferences": {
            "FeederFixes": ["RIVET", "WELSH"],
            "WakeCategories": ["SuperHeavy", "Heavy"]
          } 
        },
        { "Identifier": "07" },
        {
          "Identifier": "16R",
          "Preferences": {
            "FeederFixes": ["RIVET", "WELSH"],
            "WakeCategories": ["SuperHeavy", "Heavy"]
          } 
        },
        { 
          "Identifier": "34R",
          "Preferences": {
            "FeederFixes": ["BOREE", "YAKKA", "MARLN"]
          }
        },
        { "Identifier": "25" }
      ],
      "RunwayModes": [
        {
          "Identifier": "34IVA",
          "Runways": [
            { "Identifier": "34L", "LandingRateSeconds": 180 },
            { "Identifier": "34R", "LandingRateSeconds": 180 }
          ]
        },
        {
          "Identifier": "34I",
          "Runways": [
            { "Identifier": "34L", "LandingRateSeconds": 210, "Dependencies":[{ "RunwayIdentifier": "34R", "SeparationSeconds": 60 }] },
            { "Identifier": "34R", "LandingRateSeconds": 210, "Dependencies":[{ "RunwayIdentifier": "34L", "SeparationSeconds": 60 }] }
          ]
        },
        {
          "Identifier": "16IVA",
          "Runways": [
            { "Identifier": "16R", "LandingRateSeconds": 180 },
            { "Identifier": "16L", "LandingRateSeconds": 180 }
          ]
        },
        {
          "Identifier": "16I",
          "Runways": [
            { "Identifier": "16R", "LandingRateSeconds": 210, "Dependencies":[{ "RunwayIdentifier": "16L", "SeparationSeconds": 60 }] },
            { "Identifier": "16L", "LandingRateSeconds": 210, "Dependencies":[{ "RunwayIdentifier": "16R", "SeparationSeconds": 60 }] }
          ]
        },
        {
          "Identifier": "25I",
          "Runways": [
            { "Identifier": "25", "LandingRateSeconds": 210 }
          ]
        },
        {
          "Identifier": "07I",
          "Runways": [
            { "Identifier": "07", "LandingRateSeconds": 210 }
          ]
        },
        {
          "Identifier": "SODPROPS",
          "Runways": [
            { "Identifier": "34L", "LandingRateSeconds": 300 }
          ]
        }
      ],
      "Arrivals": [
        {
          "FeederFix": "BOREE",

          "ArrivalRegex": "/BORE\\d[AP]/",
          "Category": "Jet",
          "AdditionalAircraftTypes": ["DH8D"],
          "RunwayIntervals": {
            "34L": 17,
            "34R": 17,
            "16L": 11,
            "16R": 11,
            "07": 15,
            "25": 14
          }
        },
        {
          "FeederFix": "BOREE",

          "ArrivalRegex": "/BORE\\d[AP]/",
          "Category": "NonJet",
          "RunwayIntervals": {
            "34L": 20,
            "34R": 20,
            "16L": 12,
            "16R": 12,
            "07": 17,
            "25": 16
          }
        },
        {
          "FeederFix": "YAKKA",
          "ArrivalRegex": "/MEPIL\\d/",
          "Category": "Jet",
          "AdditionalAircraftTypes": ["DH8D"],
          "RunwayIntervals": {
            "34L": 18,
            "34R": 18,
            "16L": 12,
            "16R": 11,
            "07": 15,
            "25": 15
          }
        },
        {
          "FeederFix": "YAKKA",
          "ArrivalRegex": "/MEPIL\\d/",
          "Category": "NonJet",
          "RunwayIntervals": {
            "34L": 20,
            "34R": 20,
            "16L": 13,
            "16R": 13,
            "07": 17,
            "25": 16
          }
        },
        {
          "FeederFix": "MARLN",
          "ArrivalRegex": "/MARLN\\d/",
          "Category": "Jet",
          "AdditionalAircraftTypes": ["DH8D"],
          "RunwayIntervals": {
            "34L": 18,
            "34R": 15,
            "16L": 17,
            "16R": 17,
            "07": 16,
            "25": 12
          }
        },
        {
          "FeederFix": "MARLN",
          "ArrivalRegex": "/MARLN\\d/",
          "Category": "NonJet",
          "RunwayIntervals": {
            "34L": 20,
            "34R": 17,
            "16L": 19,
            "16R": 20,
            "07": 18,
            "25": 13
          }
        },
        {
          "FeederFix": "RIVET",
          "ArrivalRegex": "/RIVET\\d/",
          "Category": "Jet",
          "AdditionalAircraftTypes": ["DH8D"],
          "RunwayIntervals": {
            "34L": 15,
            "34R": 18,
            "16L": 18,
            "16R": 15,
            "07": 11,
            "25": 16
          }
        },
        {
          "FeederFix": "RIVET",
          "ArrivalRegex": "/RIVET\\d/",
          "Category": "NonJet",
          "RunwayIntervals": {
            "34L": 17,
            "34R": 20,
            "16L": 20,
            "16R": 17,
            "07": 12,
            "25": 18
          }
        },
        {
          "FeederFix": "WELSH",
          "ArrivalRegex": "/ODALE\\d/",
          "Category": "Jet",
          "AdditionalAircraftTypes": ["DH8D"],
          "RunwayIntervals": {
            "34L": 16,
            "34R": 18,
            "16L": 18,
            "16R": 16,
            "07": 11,
            "25": 17
          }
        },
        {
          "FeederFix": "WELSH",
          "ArrivalRegex": "/ODALE\\d/",
          "Category": "NonJet",
          "RunwayIntervals": {
            "34L": 18,
            "34R": 20,
            "16L": 21,
            "16R": 18,
            "07": 13,
            "25": 19
          }
        }
      ],
      "Views": [
        {
          "Identifier": "GUN/BIK",
          "ViewMode": "Enroute",
          "TimeHorizonMinutes": 30,
          "LeftLadder": ["RIVET"],
          "RightLadder": ["WELSH"]
        },
        {
          "Identifier": "ARL",
          "ViewMode": "Enroute",
          "TimeHorizonMinutes": 30,
          "LeftLadder": ["BOREE"],
          "RightLadder": ["YAKKA"]
        },
        {
          "Identifier": "OCN",
          "ViewMode": "Enroute",
          "TimeHorizonMinutes": 30,
          "LeftLadder": ["MARLN"],
          "RightLadder": []
        },
        {
          "Identifier": "ARL/OCN",
          "ViewMode": "Enroute",
          "TimeHorizonMinutes": 30,
          "LeftLadder": ["BOREE", "YAKKA"],
          "RightLadder": ["MARLN"]
        },
        {
          "Identifier": "ALL",
          "ViewMode": "Enroute",
          "TimeHorizonMinutes": 30,
          "LeftLadder": ["RIVET", "WELSH"],
          "RightLadder": ["YAKKA", "MARLN", "BOREE"]
        },
        {
          "Identifier": "RWY",
          "ViewMode": "Approach",
          "TimeHorizonMinutes": 45,
          "LeftLadder": ["34L", "16R", "07"],
          "RightLadder": ["34R", "16L", "25"]
        }
      ],
      "DepartureAirports": [
        {
          "Identifier": "YPMQ",
          "Distance": 209.0,
          "FlightTimes": [
            {
              "AircraftType": "JET",
              "AverageFlightTime": "00:44:53.4000000"
            },
            {
              "AircraftType": "NONJET",
              "AverageFlightTime": "00:41:57"
            }
          ]
        },
        {
          "Identifier": "YCOM",
          "Distance": 221.0,
          "FlightTimes": [
            {
              "AircraftType": "JET",
              "AverageFlightTime": "00:46:45"
            },
            {
              "AircraftType": "NONJET",
              "AverageFlightTime": "00:43:43.8000000"
            }
          ]
        },
        {
          "Identifier": "YSCB",
          "Distance": 178.0,
          "FlightTimes": [
            {
              "AircraftType": "JET",
              "AverageFlightTime": "00:40:05.4000000"
            },
            {
              "AircraftType": "NONJET",
              "AverageFlightTime": "00:37:21.6000000"
            }
          ]
        },
        {
          "Identifier": "YGLB",
          "Distance": 111.0,
          "FlightTimes": [
            {
              "AircraftType": "JET",
              "AverageFlightTime": "00:29:42.6000000"
            },
            {
              "AircraftType": "NONJET",
              "AverageFlightTime": "00:27:25.8000000"
            }
          ]
        },
        {
          "Identifier": "YCWR",
          "Distance": 163.0,
          "FlightTimes": [
            {
              "AircraftType": "JET",
              "AverageFlightTime": "00:37:45.6000000"
            },
            {
              "AircraftType": "NONJET",
              "AverageFlightTime": "00:35:08.4000000"
            }
          ]
        },
        {
          "Identifier": "YPKS",
          "Distance": 221.0,
          "FlightTimes": [
            {
              "AircraftType": "JET",
              "AverageFlightTime": "00:46:45"
            },
            {
              "AircraftType": "NONJET",
              "AverageFlightTime": "00:43:43.8000000"
            }
          ]
        },
        {
          "Identifier": "YORG",
          "Distance": 140.0,
          "FlightTimes": [
            {
              "AircraftType": "JET",
              "AverageFlightTime": "00:34:12"
            },
            {
              "AircraftType": "NONJET",
              "AverageFlightTime": "00:31:43.8000000"
            }
          ]
        },
        {
          "Identifier": "YBTH",
          "Distance": 175.0,
          "FlightTimes": [
            {
              "AircraftType": "JET",
              "AverageFlightTime": "00:39:37.2000000"
            },
            {
              "AircraftType": "NONJET",
              "AverageFlightTime": "00:36:55.2000000"
            }
          ]
        },
        {
          "Identifier": "YSDU",
          "Distance": 214.0,
          "FlightTimes": [
            {
              "AircraftType": "JET",
              "AverageFlightTime": "00:45:40.2000000"
            },
            {
              "AircraftType": "NONJET",
              "AverageFlightTime": "00:42:41.4000000"
            }
          ]
        },
        {
          "Identifier": "YSCO",
          "Distance": 117.0,
          "FlightTimes": [
            {
              "AircraftType": "JET",
              "AverageFlightTime": "00:30:38.4000000"
            },
            {
              "AircraftType": "NONJET",
              "AverageFlightTime": "00:28:19.2000000"
            }
          ]
        },
        {
          "Identifier": "YSTW",
          "Distance": 191.0,
          "FlightTimes": [
            {
              "AircraftType": "JET",
              "AverageFlightTime": "00:42:06"
            },
            {
              "AircraftType": "NONJET",
              "AverageFlightTime": "00:39:17.4000000"
            }
          ]
        },
        {
          "Identifier": "YARM",
          "Distance": 214.0,
          "FlightTimes": [
            {
              "AircraftType": "JET",
              "AverageFlightTime": "00:45:40.2000000"
            },
            {
              "AircraftType": "NONJET",
              "AverageFlightTime": "00:42:41.4000000"
            }
          ]
        },
        {
          "Identifier": "YGFN",
          "Distance": 298.0,
          "FlightTimes": [
            {
              "AircraftType": "JET",
              "AverageFlightTime": "00:58:40.8000000"
            },
            {
              "AircraftType": "NONJET",
              "AverageFlightTime": "00:55:08.4000000"
            }
          ]
        },
        {
          "Identifier": "YNBR",
          "Distance": 255.0,
          "FlightTimes": [
            {
              "AircraftType": "JET",
              "AverageFlightTime": "00:52:01.2000000"
            },
            {
              "AircraftType": "NONJET",
              "AverageFlightTime": "00:48:46.2000000"
            }
          ]
        },
        {
          "Identifier": "YCBB",
          "Distance": 194.0,
          "FlightTimes": [
            {
              "AircraftType": "JET",
              "AverageFlightTime": "00:42:34.2000000"
            },
            {
              "AircraftType": "NONJET",
              "AverageFlightTime": "00:39:43.8000000"
            }
          ]
        },
        {
          "Identifier": "YSDU",
          "Distance": 249.0,
          "FlightTimes": [
            {
              "AircraftType": "JET",
              "AverageFlightTime": "00:51:05.4000000"
            },
            {
              "AircraftType": "NONJET",
              "AverageFlightTime": "00:47:52.8000000"
            }
          ]
        },
        {
          "Identifier": "YMDG",
          "Distance": 179.0,
          "FlightTimes": [
            {
              "AircraftType": "JET",
              "AverageFlightTime": "00:40:14.4000000"
            },
            {
              "AircraftType": "NONJET",
              "AverageFlightTime": "00:37:30.6000000"
            }
          ]
        },
        {
          "Identifier": "YMAY",
          "Distance": 286.0,
          "FlightTimes": [
            {
              "AircraftType": "JET",
              "AverageFlightTime": "00:56:49.2000000"
            },
            {
              "AircraftType": "NONJET",
              "AverageFlightTime": "00:53:21.6000000"
            }
          ]
        },
        {
          "Identifier": "YSWG",
          "Distance": 214.0,
          "FlightTimes": [
            {
              "AircraftType": "JET",
              "AverageFlightTime": "00:45:40.2000000"
            },
            {
              "AircraftType": "NONJET",
              "AverageFlightTime": "00:42:41.4000000"
            }
          ]
        },
        {
          "Identifier": "YMER",
          "Distance": 236.0,
          "FlightTimes": [
            {
              "AircraftType": "JET",
              "AverageFlightTime": "00:49:04.2000000"
            },
            {
              "AircraftType": "NONJET",
              "AverageFlightTime": "00:45:57"
            }
          ]
        }
      ]
    },
    {
      "Identifier": "YMML",
      "FeederFixes": ["ARBEY", "BOYSE", "BOOIN", "RAZZI", "PORTS", "ALAXO"],
      "Runways": [
        { "Identifier": "09" },
        { "Identifier": "16" },
        { "Identifier": "27" },
        { "Identifier": "34" }
      ],
      "RunwayModes": [
        {
          "Identifier": "09",
          "Runways": [
            { "Identifier": "09", "LandingRateSeconds": 180 }
          ]
        },
        {
          "Identifier": "16",
          "Runways": [
            { "Identifier": "16", "LandingRateSeconds": 180 }
          ]
        },
        {
          "Identifier": "27",
          "Runways": [
            { "Identifier": "27", "LandingRateSeconds": 180 }
          ]
        },
        {
          "Identifier": "34",
          "Runways": [
            { "Identifier": "34", "LandingRateSeconds": 180 }
          ]
        },
        {
          "Identifier": "34/27",
          "Runways": [
            { "Identifier": "34", "LandingRateSeconds": 180, "Dependencies": [{"RunwayIdentifier": "27", "SeparationSeconds": 60}]  },
            { "Identifier": "27", "LandingRateSeconds": 180, "Dependencies": [{"RunwayIdentifier": "27", "SeparationSeconds": 60}]  }
          ]
        },
        {
          "Identifier": "34/09",
          "Runways": [
            { "Identifier": "34", "LandingRateSeconds": 180, "Dependencies": [{"RunwayIdentifier": "27", "SeparationSeconds": 60}]  },
            { "Identifier": "09", "LandingRateSeconds": 180, "Dependencies": [{"RunwayIdentifier": "27", "SeparationSeconds": 60}]  }
          ]
        },
        {
          "Identifier": "16/27",
          "Runways": [
            { "Identifier": "16", "LandingRateSeconds": 180 },
            { "Identifier": "27", "LandingRateSeconds": 180 }
          ]
        },
        {
          "Identifier": "16/09",
          "Runways": [
            { "Identifier": "16", "LandingRateSeconds": 180 },
            { "Identifier": "09", "LandingRateSeconds": 180 }
          ]
        }
      ],
      "Arrivals": [
        {
          "FeederFix": "ARBEY",
          "ArrivalRegex": "/ARBE\\dA/",
          "Category": "Jet",
          "AdditionalAircraftTypes": ["DH8D"],
          "RunwayIntervals": {
            "09": 11,
            "16": 9,
            "27": 12,
            "34": 13
          }
        },
        {
          "FeederFix": "ARBEY",
          "ArrivalRegex": "/ARBE\\dA/",
          "Category": "NonJet",
          "RunwayIntervals": {
            "09": 12,
            "16": 10,
            "27": 14,
            "34": 15
          }
        },
        {
          "FeederFix": "BOOIN",
          "ArrivalRegex": "/BOIN\\dA/",
          "Category": "Jet",
          "AdditionalAircraftTypes": ["DH8D"],
          "RunwayIntervals": {
            "09": 15,
            "16": 12,
            "27": 10,
            "34": 13
          }
        },
        {
            "FeederFix": "BOOIN",
            "ArrivalRegex": "/BOIN\\dV/",
            "Category": "Jet",
            "AdditionalAircraftTypes": ["DH8D"],
            "RunwayIntervals": {
              "34": 12
            }
        },
        {
          "FeederFix": "BOOIN",
          "ArrivalRegex": "/BOIN\\dA/",
          "Category": "NonJet",
          "RunwayIntervals": {
            "09": 17,
            "16": 14,
            "27": 11,
            "34": 15
          }
        },
        {
            "FeederFix": "BOOIN",
            "ArrivalRegex": "/BOIN\\dV/",
            "Category": "NonJet",
            "RunwayIntervals": {
              "34": 14
            }
        },
        {
          "FeederFix": "BOYSE",
          "ArrivalRegex": "/BOYS\\dA/",
          "Category": "NonJet",
          "RunwayIntervals": {
            "09": 18,
            "16": 15,
            "27": 13,
            "34": 16
          }
        },
        {
          "FeederFix": "BOYSE",
          "ArrivalRegex": "/BOYS\\dV/",
          "Category": "NonJet",
          "RunwayIntervals": {
            "34": 15
          }
        },
        {
          "FeederFix": "RAZZI",
          "ArrivalRegex": "/RAZI\\d[AV]/",
          "Category": "Jet",
          "AdditionalAircraftTypes": ["DH8D"],
          "RunwayIntervals": {
            "09": 16,
            "16": 13,
            "27": 9,
            "34": 10
          }
        },
        {
          "FeederFix": "RAZZI",
          "ArrivalRegex": "/RAZI\\d[AV]/",
          "Category": "NonJet",
          "RunwayIntervals": {
            "09": 18,
            "16": 15,
            "27": 10,
            "34": 11
          }
        },
        {
          "FeederFix": "RAZZI",
          "ArrivalRegex": "/RAZI\\dM/",
          "Category": "Jet",
          "AdditionalAircraftTypes": ["DH8D"],
          "RunwayIntervals": {
            "16": 11
          }
        },
        {
          "FeederFix": "RAZZI",
          "ArrivalRegex": "/RAZI\\dM/",
          "Category": "NonJet",
          "RunwayIntervals": {
            "16": 13
          }
        },
        {
          "FeederFix": "PORTS",
          "ArrivalRegex": "/PORT\\dA/",
          "Category": "Jet",
          "AdditionalAircraftTypes": ["DH8D"],
          "RunwayIntervals": {
            "09": 11,
            "34": 7
          }
        },
        {
          "FeederFix": "PORTS",
          "ArrivalRegex": "/PORT\\dA/",
          "Category": "NonJet",
          "RunwayIntervals": {
            "09": 12,
            "34": 8
          }
        },
        {
          "FeederFix": "ALAXO",
          "ArrivalRegex": "/ALAX\\dA/",
          "Category": "Jet",
          "AdditionalAircraftTypes": ["DH8D"],
          "RunwayIntervals": {
            "09": 11,
            "16": 17,
            "27": 15,
            "34": 12
          }
        },
        {
          "FeederFix": "ALAXO",
          "ArrivalRegex": "/ALAX\\dA/",
          "Category": "NonJet",
          "RunwayIntervals": {
            "09": 12,
            "16": 19,
            "27": 17,
            "34": 14
          }
        },
        {
          "FeederFix": "ALAXO",
          "ArrivalRegex": "/ALAX\\dP/",
          "Category": "Jet",
          "AdditionalAircraftTypes": ["DH8D"],
          "RunwayIntervals": {
            "16": 15
          }
        },
        {
          "FeederFix": "ALAXO",
          "ArrivalRegex": "/ALAX\\dP/",
          "Category": "NonJet",
          "RunwayIntervals": {
            "16": 17
          }
        }
      ],
      "Views": [
        {
          "Identifier": "BLA/ELW",
          "ViewMode": "Enroute",
          "TimeHorizonMinutes": 30,
          "LeftLadder": ["BOOIN"],
          "RightLadder": ["BOYSE"]
        },
        {
          "Identifier": "MUN/YWE",
          "ViewMode": "Enroute",
          "TimeHorizonMinutes": 30,
          "LeftLadder": ["ARBEY"],
          "RightLadder": ["ALAXO"]
        },
        {
          "Identifier": "HUO/WON",
          "ViewMode": "Enroute",
          "TimeHorizonMinutes": 30,
          "LeftLadder": ["RAZZI"],
          "RightLadder": ["PORTS"]
        },
        {
          "Identifier": "ALL",
          "ViewMode": "Enroute",
          "TimeHorizonMinutes": 30,
          "LeftLadder": ["ARBEY", "ALAXO", "PORTS"],
          "RightLadder": ["BOOIN", "BOYSE", "RAZZI"]
        },
        {
          "Identifier": "RWY",
          "ViewMode": "Approach",
          "TimeHorizonMinutes": 45,
          "LeftLadder": ["16", "34"],
          "RightLadder": ["09", "27"]
        }
      ],
      "DepartureAirports": [
        {
          "Identifier": "YHAY",
          "Distance": 214.0,
          "FlightTimes": [
            {
              "AircraftType": "JET",
              "AverageFlightTime": "00:45:40.2000000"
            },
            {
              "AircraftType": "NONJET",
              "AverageFlightTime": "00:42:41.4000000"
            }
          ]
        },
        {
          "Identifier": "YDLQ",
          "Distance": 147.0,
          "FlightTimes": [
            {
              "AircraftType": "JET",
              "AverageFlightTime": "00:35:17.4000000"
            },
            {
              "AircraftType": "NONJET",
              "AverageFlightTime": "00:32:46.2000000"
            }
          ]
        },
        {
          "Identifier": "YECH",
          "Distance": 93.0,
          "FlightTimes": [
            {
              "AircraftType": "JET",
              "AverageFlightTime": "00:26:55.2000000"
            },
            {
              "AircraftType": "NONJET",
              "AverageFlightTime": "00:24:46.2000000"
            }
          ]
        },
        {
          "Identifier": "YMNG",
          "Distance": 78.0,
          "FlightTimes": [
            {
              "AircraftType": "JET",
              "AverageFlightTime": "00:24:36"
            },
            {
              "AircraftType": "NONJET",
              "AverageFlightTime": "00:22:33"
            }
          ]
        },
        {
          "Identifier": "YSHT",
          "Distance": 114.0,
          "FlightTimes": [
            {
              "AircraftType": "JET",
              "AverageFlightTime": "00:30:10.2000000"
            },
            {
              "AircraftType": "NONJET",
              "AverageFlightTime": "00:27:52.8000000"
            }
          ]
        },
        {
          "Identifier": "YNAR",
          "Distance": 225.0,
          "FlightTimes": [
            {
              "AircraftType": "JET",
              "AverageFlightTime": "00:47:22.2000000"
            },
            {
              "AircraftType": "NONJET",
              "AverageFlightTime": "00:44:19.2000000"
            }
          ]
        },
        {
          "Identifier": "YCOR",
          "Distance": 158.0,
          "FlightTimes": [
            {
              "AircraftType": "JET",
              "AverageFlightTime": "00:36:59.4000000"
            },
            {
              "AircraftType": "NONJET",
              "AverageFlightTime": "00:34:24"
            }
          ]
        },
        {
          "Identifier": "YBLA",
          "Distance": 126.0,
          "FlightTimes": [
            {
              "AircraftType": "JET",
              "AverageFlightTime": "00:32:01.8000000"
            },
            {
              "AircraftType": "NONJET",
              "AverageFlightTime": "00:29:39.6000000"
            }
          ]
        },
        {
          "Identifier": "YWGT",
          "Distance": 116.0,
          "FlightTimes": [
            {
              "AircraftType": "JET",
              "AverageFlightTime": "00:30:28.8000000"
            },
            {
              "AircraftType": "NONJET",
              "AverageFlightTime": "00:28:10.8000000"
            }
          ]
        },
        {
          "Identifier": "YMAY",
          "Distance": 154.0,
          "FlightTimes": [
            {
              "AircraftType": "JET",
              "AverageFlightTime": "00:36:22.2000000"
            },
            {
              "AircraftType": "NONJET",
              "AverageFlightTime": "00:33:48"
            }
          ]
        },
        {
          "Identifier": "YSWG",
          "Distance": 210.0,
          "FlightTimes": [
            {
              "AircraftType": "JET",
              "AverageFlightTime": "00:45:03"
            },
            {
              "AircraftType": "NONJET",
              "AverageFlightTime": "00:42:06"
            }
          ]
        },
        {
          "Identifier": "YCRG",
          "Distance": 205.0,
          "FlightTimes": [
            {
              "AircraftType": "JET",
              "AverageFlightTime": "00:44:16.2000000"
            },
            {
              "AircraftType": "NONJET",
              "AverageFlightTime": "00:41:21.6000000"
            }
          ]
        },
        {
          "Identifier": "YHOT",
          "Distance": 139.0,
          "FlightTimes": [
            {
              "AircraftType": "JET",
              "AverageFlightTime": "00:34:03"
            },
            {
              "AircraftType": "NONJET",
              "AverageFlightTime": "00:31:34.8000000"
            }
          ]
        },
        {
          "Identifier": "YLTV",
          "Distance": 130.0,
          "FlightTimes": [
            {
              "AircraftType": "JET",
              "AverageFlightTime": "00:32:39"
            },
            {
              "AircraftType": "NONJET",
              "AverageFlightTime": "00:30:15"
            }
          ]
        },
        {
          "Identifier": "YFLI",
          "Distance": 251.0,
          "FlightTimes": [
            {
              "AircraftType": "JET",
              "AverageFlightTime": "00:51:24"
            },
            {
              "AircraftType": "NONJET",
              "AverageFlightTime": "00:48:10.2000000"
            }
          ]
        },
        {
          "Identifier": "YDPO",
          "Distance": 249.0,
          "FlightTimes": [
            {
              "AircraftType": "JET",
              "AverageFlightTime": "00:51:05.4000000"
            },
            {
              "AircraftType": "NONJET",
              "AverageFlightTime": "00:47:52.8000000"
            }
          ]
        },
        {
          "Identifier": "YMLT",
          "Distance": 282.0,
          "FlightTimes": [
            {
              "AircraftType": "JET",
              "AverageFlightTime": "00:56:12"
            },
            {
              "AircraftType": "NONJET",
              "AverageFlightTime": "00:52:46.2000000"
            }
          ]
        },
        {
          "Identifier": "YWYY",
          "Distance": 243.0,
          "FlightTimes": [
            {
              "AircraftType": "JET",
              "AverageFlightTime": "00:50:09.6000000"
            },
            {
              "AircraftType": "NONJET",
              "AverageFlightTime": "00:46:59.4000000"
            }
          ]
        },
        {
          "Identifier": "YKII",
          "Distance": 199.0,
          "FlightTimes": [
            {
              "AircraftType": "JET",
              "AverageFlightTime": "00:43:20.4000000"
            },
            {
              "AircraftType": "NONJET",
              "AverageFlightTime": "00:40:28.2000000"
            }
          ]
        },
        {
          "Identifier": "YWBL",
          "Distance": 174.0,
          "FlightTimes": [
            {
              "AircraftType": "JET",
              "AverageFlightTime": "00:39:28.2000000"
            },
            {
              "AircraftType": "NONJET",
              "AverageFlightTime": "00:36:46.2000000"
            }
          ]
        },
        {
          "Identifier": "YPOD",
          "Distance": 189.0,
          "FlightTimes": [
            {
              "AircraftType": "JET",
              "AverageFlightTime": "00:41:47.4000000"
            },
            {
              "AircraftType": "NONJET",
              "AverageFlightTime": "00:38:59.4000000"
            }
          ]
        },
        {
          "Identifier": "YMTG",
          "Distance": 209.0,
          "FlightTimes": [
            {
              "AircraftType": "JET",
              "AverageFlightTime": "00:44:53.4000000"
            },
            {
              "AircraftType": "NONJET",
              "AverageFlightTime": "00:41:57"
            }
          ]
        },
        {
          "Identifier": "YHML",
          "Distance": 203.0,
          "FlightTimes": [
            {
              "AircraftType": "JET",
              "AverageFlightTime": "00:43:57.6000000"
            },
            {
              "AircraftType": "NONJET",
              "AverageFlightTime": "00:41:03.6000000"
            }
          ]
        },
        {
          "Identifier": "YBLT",
          "Distance": 70.0,
          "FlightTimes": [
            {
              "AircraftType": "JET",
              "AverageFlightTime": "00:23:21.6000000"
            },
            {
              "AircraftType": "NONJET",
              "AverageFlightTime": "00:21:21.6000000"
            }
          ]
        },
        {
          "Identifier": "YARA",
          "Distance": 163.0,
          "FlightTimes": [
            {
              "AircraftType": "JET",
              "AverageFlightTime": "00:37:45.6000000"
            },
            {
              "AircraftType": "NONJET",
              "AverageFlightTime": "00:35:08.4000000"
            }
          ]
        },
        {
          "Identifier": "YSWL",
          "Distance": 174.0,
          "FlightTimes": [
            {
              "AircraftType": "JET",
              "AverageFlightTime": "00:39:28.2000000"
            },
            {
              "AircraftType": "NONJET",
              "AverageFlightTime": "00:36:46.2000000"
            }
          ]
        },
        {
          "Identifier": "YNRC",
          "Distance": 257.0,
          "FlightTimes": [
            {
              "AircraftType": "JET",
              "AverageFlightTime": "00:52:19.8000000"
            },
            {
              "AircraftType": "NONJET",
              "AverageFlightTime": "00:49:03.6000000"
            }
          ]
        },
        {
          "Identifier": "YHSM",
          "Distance": 167.0,
          "FlightTimes": [
            {
              "AircraftType": "JET",
              "AverageFlightTime": "00:38:22.8000000"
            },
            {
              "AircraftType": "NONJET",
              "AverageFlightTime": "00:35:43.8000000"
            }
          ]
        },
        {
          "Identifier": "YHNL",
          "Distance": 203.0,
          "FlightTimes": [
            {
              "AircraftType": "JET",
              "AverageFlightTime": "00:43:57.6000000"
            },
            {
              "AircraftType": "NONJET",
              "AverageFlightTime": "00:41:03.6000000"
            }
          ]
        },
        {
          "Identifier": "YWKB",
          "Distance": 170.0,
          "FlightTimes": [
            {
              "AircraftType": "JET",
              "AverageFlightTime": "00:38:51"
            },
            {
              "AircraftType": "NONJET",
              "AverageFlightTime": "00:36:10.2000000"
            }
          ]
        },
        {
          "Identifier": "YBDG",
          "Distance": 83.0,
          "FlightTimes": [
            {
              "AircraftType": "JET",
              "AverageFlightTime": "00:25:22.2000000"
            },
            {
              "AircraftType": "NONJET",
              "AverageFlightTime": "00:23:17.4000000"
            }
          ]
        },
        {
          "Identifier": "YSWH",
          "Distance": 153.0,
          "FlightTimes": [
            {
              "AircraftType": "JET",
              "AverageFlightTime": "00:36:13.2000000"
            },
            {
              "AircraftType": "NONJET",
              "AverageFlightTime": "00:33:39.6000000"
            }
          ]
        },
        {
          "Identifier": "YGTH",
          "Distance": 234.0,
          "FlightTimes": [
            {
              "AircraftType": "JET",
              "AverageFlightTime": "00:48:45.6000000"
            },
            {
              "AircraftType": "NONJET",
              "AverageFlightTime": "00:45:39.6000000"
            }
          ]
        },
        {
          "Identifier": "YCOM",
          "Distance": 233.0,
          "FlightTimes": [
            {
              "AircraftType": "JET",
              "AverageFlightTime": "00:48:36.6000000"
            },
            {
              "AircraftType": "NONJET",
              "AverageFlightTime": "00:45:30.6000000"
            }
          ]
        }
      ]
    },
    {
      "Identifier": "YBBN",
      "FeederFixes": ["BLAKA", "GOMOL", "ENLIP", "MORBI", "SMOKA", "TEBOT", "UGTUG", "WOODY"],
      "PreferredRunways": {
        "ENLIP": ["01L", "19R"],
        "WOODY": ["01L", "19R"],
        "MORBI": ["01L", "19R"],
        "SMOKA": ["01L", "19R"],
        "BLAKA": ["01R", "19L"],
        "GOMOL": ["01R", "19L"],
        "TEBOT": ["01R", "19L"],
        "UGTUG": ["01R", "19L"]
      },
      "Runways": [
        { 
          "Identifier": "01L"
        },
        { 
          "Identifier": "01R"
        },
        { 
          "Identifier": "19L"
        },
        { 
          "Identifier": "19R"
        }
      ],
      "RunwayModes": [
        {
          "Identifier": "19",
          "Runways": [
            { "Identifier": "19L", "LandingRateSeconds": 180 },
            { "Identifier": "19R", "LandingRateSeconds": 180 }
          ]
        },
        {
          "Identifier": "01",
          "Runways": [
            { "Identifier": "01L", "LandingRateSeconds": 180 },
            { "Identifier": "01R", "LandingRateSeconds": 180 }
          ]
        },
        {
          "Identifier": "SODPROPS",
          "Runways": [
            { "Identifier": "19R", "LandingRateSeconds": 300 }
          ]
        },
        {
          "Identifier": "RECIP",
          "Runways": [
            { "Identifier": "19L", "LandingRateSeconds": 240 },
            { "Identifier": "19R", "LandingRateSeconds": 240 }
          ]
        }
      ],
      "Arrivals": [
        {
          "FeederFix": "BLAKA",
          "ArrivalRegex": "/BLAK\\dA/",
          "Category": "Jet",
          "AdditionalAircraftTypes": ["DH8D"],
          "RunwayIntervals": {
            "01L": 13,
            "01R": 13,
            "19L": 19,
            "19R": 21
          }
        },
        {
          "FeederFix": "BLAKA",
          "ArrivalRegex": "/BLAK\\dA/",
          "Category": "NonJet",
          "RunwayIntervals": {
            "01L": 15,
            "01R": 15,
            "19L": 22,
            "19R": 24
          }
        },
        {
          "FeederFix": "BLAKA",
          "ArrivalRegex": "/BLAK\\dX/",
          "Category": "Jet",
          "AdditionalAircraftTypes": ["DH8D"],
          "RunwayIntervals": {
            "01R": 12,
            "19L": 16
          }
        },
        {
          "FeederFix": "BLAKA",
          "ArrivalRegex": "/BLAK\\dX/",
          "Category": "NonJet",
          "RunwayIntervals": {
            "01R": 14,
            "19L": 18
          }
        },
        {
          "FeederFix": "BLAKA",
          "ArrivalRegex": "/ISPON\\d/",
          "Category": "Jet",
          "AdditionalAircraftTypes": ["DH8D"],
          "RunwayIntervals": {
            "19R": 19
          }
        },
        {
          "FeederFix": "BLAKA",
          "ArrivalRegex": "/ISPON\\d/",
          "Category": "Jet",
          "AdditionalAircraftTypes": ["DH8D"],
          "RunwayIntervals": {
            "19R": 22
          }
        },
        {
          "FeederFix": "ENLIP",
          "ArrivalRegex": "/ENLI\\dA/",
          "Category": "Jet",
          "AdditionalAircraftTypes": ["DH8D"],
          "RunwayIntervals": {
            "01L": 11,
            "01R": 11,
            "19L": 20,
            "19R": 18
          }
        },
        {
          "FeederFix": "ENLIP",
          "ArrivalRegex": "/ENLI\\dA/",
          "Category": "NonJet",
          "RunwayIntervals": {
            "01L": 13,
            "01R": 13,
            "19L": 23,
            "19R": 20
          }
        },
        {
          "FeederFix": "ENLIP",
          "ArrivalRegex": "/ENLI\\dX/",
          "Category": "Jet",
          "AdditionalAircraftTypes": ["DH8D"],
          "RunwayIntervals": {
            "19L": 16,
            "19R": 16
          }
        },
        {
          "FeederFix": "ENLIP",
          "ArrivalRegex": "/ENLI\\dX/",
          "Category": "NonJet",
          "RunwayIntervals": {
            "19L": 19,
            "19R": 18
          }
        },
        {
          "FeederFix": "ENLIP",
          "ArrivalRegex": "/ISPON\\d/",
          "Category": "Jet",
          "AdditionalAircraftTypes": ["DH8D"],
          "RunwayIntervals": {
            "19R": 20
          }
        },
        {
          "FeederFix": "ENLIP",
          "ArrivalRegex": "/ISPON\\d/",
          "Category": "NonJet",
          "RunwayIntervals": {
            "19R": 23
          }
        },
        {
          "FeederFix": "GOMOL",
          "ArrivalRegex": "/GOMO\\dA/",
          "Category": "Jet",
          "AdditionalAircraftTypes": ["DH8D"],
          "RunwayIntervals": {
            "01L": 14,
            "01R": 14,
            "19L": 18,
            "19R": 20
          }
        },
        {
          "FeederFix": "GOMOL",
          "ArrivalRegex": "/GOMO\\dA/",
          "Category": "NonJet",
          "RunwayIntervals": {
            "01L": 16,
            "01R": 15,
            "19L": 21,
            "19R": 23
          }
        },
        {
          "FeederFix": "GOMOL",
          "ArrivalRegex": "/GOMO\\dV/",
          "Category": "Jet",
          "AdditionalAircraftTypes": ["DH8D"],
          "RunwayIntervals": {
            "01R": 13,
            "19L": 15
          }
        },
        {
          "FeederFix": "GOMOL",
          "ArrivalRegex": "/GOMO\\dV/",
          "Category": "NonJet",
          "RunwayIntervals": {
            "01R": 14,
            "19L": 17
          }
        },
        {
          "FeederFix": "GOMOL",
          "ArrivalRegex": "/GOMO\\dX/",
          "Category": "Jet",
          "AdditionalAircraftTypes": ["DH8D"],
          "RunwayIntervals": {
            "01R": 12,
            "19L": 16
          }
        },
        {
          "FeederFix": "GOMOL",
          "ArrivalRegex": "/GOMO\\dX/",
          "Category": "NonJet",
          "RunwayIntervals": {
            "01R": 14,
            "19L": 18
          }
        },
        {
          "FeederFix": "GOMOL",
          "ArrivalRegex": "/ISPON\\d/",
          "Category": "Jet",
          "AdditionalAircraftTypes": ["DH8D"],
          "RunwayIntervals": {
            "19R": 19
          }
        },
        {
          "FeederFix": "GOMOL",
          "ArrivalRegex": "/ISPON\\d/",
          "Category": "NonJet",
          "RunwayIntervals": {
            "19R": 21
          }
        },
        {
          "FeederFix": "MORBI",
          "ArrivalRegex": "/MORB\\dA/",
          "Category": "Jet",
          "AdditionalAircraftTypes": ["DH8D"],
          "RunwayIntervals": {
            "01L": 16,
            "01R": 15,
            "19L": 13,
            "19R": 12
          }
        },
        {
          "FeederFix": "MORBI",
          "ArrivalRegex": "/MORB\\dA/",
          "Category": "NonJet",
          "RunwayIntervals": {
            "01L": 18,
            "01R": 17,
            "19L": 14,
            "19R": 14
          }
        },
        {
          "FeederFix": "MORBI",
          "ArrivalRegex": "/MORB\\dV/",
          "Category": "Jet",
          "AdditionalAircraftTypes": ["DH8D"],
          "RunwayIntervals": {
            "01L": 13,
            "19R": 11
          }
        },
        {
          "FeederFix": "MORBI",
          "ArrivalRegex": "/MORB\\dV/",
          "Category": "NonJet",
          "RunwayIntervals": {
            "01L": 14,
            "19R": 12
          }
        },
        {
          "FeederFix": "SMOKA",
          "ArrivalRegex": "/SMOK\\dA/",
          "Category": "Jet",
          "AdditionalAircraftTypes": ["DH8D"],
          "RunwayIntervals": {
            "01L": 15,
            "01R": 14,
            "19L": 13,
            "19R": 13
          }
        },
        {
          "FeederFix": "SMOKA",
          "ArrivalRegex": "/SMOK\\dA/",
          "Category": "NonJet",
          "RunwayIntervals": {
            "01L": 17,
            "01R": 16,
            "19L": 15,
            "19R": 15
          }
        },
        {
          "FeederFix": "SMOKA",
          "ArrivalRegex": "/SMOK\\dM/",
          "Category": "Jet",
          "AdditionalAircraftTypes": ["DH8D"],
          "RunwayIntervals": {
            "01R": 12
          }
        },
        {
          "FeederFix": "SMOKA",
          "ArrivalRegex": "/SMOK\\dM/",
          "Category": "NonJet",
          "RunwayIntervals": {
            "01R": 13
          }
        },
        {
          "FeederFix": "SMOKA",
          "ArrivalRegex": "/SMOK\\dX/",
          "Category": "Jet",
          "AdditionalAircraftTypes": ["DH8D"],
          "RunwayIntervals": {
            "01L": 13,
            "19R": 11
          }
        },
        {
          "FeederFix": "SMOKA",
          "ArrivalRegex": "/SMOK\\dX/",
          "Category": "NonJet",
          "RunwayIntervals": {
            "01L": 14,
            "19R": 13
          }
        },
        {
          "FeederFix": "TEBOT",
          "ArrivalRegex": "/TEBO\\dA/",
          "Category": "Jet",
          "AdditionalAircraftTypes": ["DH8D"],
          "RunwayIntervals": {
            "01L": 18,
            "01R": 18,
            "19L": 11,
            "19R": 11
          }
        },
        {
          "FeederFix": "TEBOT",
          "ArrivalRegex": "/TEBO\\dA/",
          "Category": "NonJet",
          "RunwayIntervals": {
            "01L": 20,
            "01R": 21,
            "19L": 12,
            "19R": 13
          }
        },
        {
          "FeederFix": "TEBOT",
          "ArrivalRegex": "/TEBO\\dX/",
          "Category": "Jet",
          "AdditionalAircraftTypes": ["DH8D"],
          "RunwayIntervals": {
            "01R": 15
          }
        },
        {
          "FeederFix": "TEBOT",
          "ArrivalRegex": "/TEBO\\dX/",
          "Category": "NonJet",
          "RunwayIntervals": {
            "01R": 17
          }
        },
        {
          "FeederFix": "UGTUG",
          "ArrivalRegex": "/UGTU\\dA/",
          "Category": "Jet",
          "AdditionalAircraftTypes": ["DH8D"],
          "RunwayIntervals": {
            "01L": 15,
            "01R": 15,
            "19L": 13,
            "19R": 14
          }
        },
        {
          "FeederFix": "UGTUG",
          "ArrivalRegex": "/UGTU\\dA/",
          "Category": "NonJet",
          "RunwayIntervals": {
            "01L": 17,
            "01R": 17,
            "19L": 15,
            "19R": 16
          }
        },
        {
          "FeederFix": "UGTUG",
          "ArrivalRegex": "/UGTU\\dX/",
          "Category": "Jet",
          "AdditionalAircraftTypes": ["DH8D"],
          "RunwayIntervals": {
            "01R": 13,
            "19L": 12
          }
        },
        {
          "FeederFix": "UGTUG",
          "ArrivalRegex": "/UGTU\\dX/",
          "Category": "NonJet",
          "RunwayIntervals": {
            "01R": 14,
            "19L": 13
          }
        },
        {
          "FeederFix": "UGTUG",
          "ArrivalRegex": "/ISPON\\d/",
          "Category": "Jet",
          "AdditionalAircraftTypes": ["DH8D"],
          "RunwayIntervals": {
            "19R": 14
          }
        },
        {
          "FeederFix": "UGTUG",
          "ArrivalRegex": "/ISPON\\d/",
          "Category": "NonJet",
          "RunwayIntervals": {
            "19R": 15
          }
        },
        {
          "FeederFix": "WOODY",
          "ArrivalRegex": "/WODY\\dA/",
          "Category": "Jet",
          "AdditionalAircraftTypes": ["DH8D"],
          "RunwayIntervals": {
            "01L": 14,
            "01R": 13,
            "19L": 15,
            "19R": 15
          }
        },
        {
          "FeederFix": "WOODY",
          "ArrivalRegex": "/WODY\\dA/",
          "Category": "NonJet",
          "RunwayIntervals": {
            "01L": 16,
            "01R": 15,
            "19L": 17,
            "19R": 16
          }
        },
        {
          "FeederFix": "WOODY",
          "ArrivalRegex": "/WODY\\dV/",
          "Category": "Jet",
          "AdditionalAircraftTypes": ["DH8D"],
          "RunwayIntervals": {
            "01L": 11,
            "19R": 12
          }
        },
        {
          "FeederFix": "WOODY",
          "ArrivalRegex": "/WODY\\dV/",
          "Category": "NonJet",
          "RunwayIntervals": {
            "01L": 13,
            "19R": 14
          }
        }
      ],
      "Views": [
        {
          "Identifier": "INL",
          "ViewMode": "Enroute",
          "TimeHorizonMinutes": 30,
          "LeftLadder": ["BLAKA"],
          "RightLadder": ["GOMOL"]
        },
        {
          "Identifier": "DOS",
          "ViewMode": "Enroute",
          "TimeHorizonMinutes": 30,
          "LeftLadder": ["ENLIP"],
          "RightLadder": ["WOODY"]
        },
        {
          "Identifier": "BUR",
          "ViewMode": "Enroute",
          "TimeHorizonMinutes": 30,
          "LeftLadder": ["MORBI"],
          "RightLadder": ["SMOKA"]
        },
        {
          "Identifier": "SDY",
          "ViewMode": "Enroute",
          "TimeHorizonMinutes": 30,
          "LeftLadder": ["TEBOT"],
          "RightLadder": ["UGTUG"] 
        },
        {
          "Identifier": "ALL",
          "ViewMode": "Enroute",
          "TimeHorizonMinutes": 30,
          "LeftLadder": ["BLAKA", "ENLIP", "GOMOL", "MORBI"],
          "RightLadder": ["SMOKA", "TEBOT", "UGTUG", "WOODY"] 
        },
        {
          "Identifier": "RWY",
          "ViewMode": "Approach",
          "TimeHorizonMinutes": 45,
          "LeftLadder": ["01L", "19R"],
          "RightLadder": ["01R", "19L"] 
        }
      ],
      "DepartureAirports": [
        {
          "Identifier": "YCFS",
          "Distance": 189.0,
          "FlightTimes": [
            {
              "AircraftType": "JET",
              "AverageFlightTime": "00:41:47.4000000"
            },
            {
              "AircraftType": "NONJET",
              "AverageFlightTime": "00:38:59.4000000"
            }
          ]
        },
        {
          "Identifier": "YGFN",
          "Distance": 158.0,
          "FlightTimes": [
            {
              "AircraftType": "JET",
              "AverageFlightTime": "00:36:59.4000000"
            },
            {
              "AircraftType": "NONJET",
              "AverageFlightTime": "00:34:24"
            }
          ]
        },
        {
          "Identifier": "YLIS",
          "Distance": 96.0,
          "FlightTimes": [
            {
              "AircraftType": "JET",
              "AverageFlightTime": "00:27:22.8000000"
            },
            {
              "AircraftType": "NONJET",
              "AverageFlightTime": "00:25:12.6000000"
            }
          ]
        },
        {
          "Identifier": "YBNA",
          "Distance": 28.0,
          "FlightTimes": [
            {
              "AircraftType": "JET",
              "AverageFlightTime": "00:16:51"
            },
            {
              "AircraftType": "NONJET",
              "AverageFlightTime": "00:15:08.4000000"
            }
          ]
        },
        {
          "Identifier": "YBCG",
          "Distance": 59.0,
          "FlightTimes": [
            {
              "AircraftType": "JET",
              "AverageFlightTime": "00:21:39"
            },
            {
              "AircraftType": "NONJET",
              "AverageFlightTime": "00:19:43.8000000"
            }
          ]
        },
        {
          "Identifier": "YARM",
          "Distance": 236.0,
          "FlightTimes": [
            {
              "AircraftType": "JET",
              "AverageFlightTime": "00:49:04.2000000"
            },
            {
              "AircraftType": "NONJET",
              "AverageFlightTime": "00:45:57"
            }
          ]
        },
        {
          "Identifier": "YGLI",
          "Distance": 172.0,
          "FlightTimes": [
            {
              "AircraftType": "JET",
              "AverageFlightTime": "00:39:09.6000000"
            },
            {
              "AircraftType": "NONJET",
              "AverageFlightTime": "00:36:28.2000000"
            }
          ]
        },
        {
          "Identifier": "YIVL",
          "Distance": 185.0,
          "FlightTimes": [
            {
              "AircraftType": "JET",
              "AverageFlightTime": "00:41:10.2000000"
            },
            {
              "AircraftType": "NONJET",
              "AverageFlightTime": "00:38:24"
            }
          ]
        },
        {
          "Identifier": "YSPE",
          "Distance": 115.0,
          "FlightTimes": [
            {
              "AircraftType": "JET",
              "AverageFlightTime": "00:30:19.8000000"
            },
            {
              "AircraftType": "NONJET",
              "AverageFlightTime": "00:28:01.8000000"
            }
          ]
        },
        {
          "Identifier": "YWCK",
          "Distance": 106.0,
          "FlightTimes": [
            {
              "AircraftType": "JET",
              "AverageFlightTime": "00:28:55.8000000"
            },
            {
              "AircraftType": "NONJET",
              "AverageFlightTime": "00:26:41.4000000"
            }
          ]
        },
        {
          "Identifier": "YMOR",
          "Distance": 243.0,
          "FlightTimes": [
            {
              "AircraftType": "JET",
              "AverageFlightTime": "00:50:09.6000000"
            },
            {
              "AircraftType": "NONJET",
              "AverageFlightTime": "00:46:59.4000000"
            }
          ]
        },
        {
          "Identifier": "YGDI",
          "Distance": 171.0,
          "FlightTimes": [
            {
              "AircraftType": "JET",
              "AverageFlightTime": "00:39:00"
            },
            {
              "AircraftType": "NONJET",
              "AverageFlightTime": "00:36:19.2000000"
            }
          ]
        },
        {
          "Identifier": "YMLS",
          "Distance": 198.0,
          "FlightTimes": [
            {
              "AircraftType": "JET",
              "AverageFlightTime": "00:43:11.4000000"
            },
            {
              "AircraftType": "NONJET",
              "AverageFlightTime": "00:40:19.2000000"
            }
          ]
        },
        {
          "Identifier": "YCCA",
          "Distance": 175.0,
          "FlightTimes": [
            {
              "AircraftType": "JET",
              "AverageFlightTime": "00:39:37.2000000"
            },
            {
              "AircraftType": "NONJET",
              "AverageFlightTime": "00:36:55.2000000"
            }
          ]
        },
        {
          "Identifier": "YKRY",
          "Distance": 102.0,
          "FlightTimes": [
            {
              "AircraftType": "JET",
              "AverageFlightTime": "00:28:18.6000000"
            },
            {
              "AircraftType": "NONJET",
              "AverageFlightTime": "00:26:06"
            }
          ]
        },
        {
          "Identifier": "YTAM",
          "Distance": 235.0,
          "FlightTimes": [
            {
              "AircraftType": "JET",
              "AverageFlightTime": "00:48:55.2000000"
            },
            {
              "AircraftType": "NONJET",
              "AverageFlightTime": "00:45:48"
            }
          ]
        },
        {
          "Identifier": "YGAY",
          "Distance": 163.0,
          "FlightTimes": [
            {
              "AircraftType": "JET",
              "AverageFlightTime": "00:37:45.6000000"
            },
            {
              "AircraftType": "NONJET",
              "AverageFlightTime": "00:35:08.4000000"
            }
          ]
        },
        {
          "Identifier": "YTNG",
          "Distance": 266.0,
          "FlightTimes": [
            {
              "AircraftType": "JET",
              "AverageFlightTime": "00:53:43.2000000"
            },
            {
              "AircraftType": "NONJET",
              "AverageFlightTime": "00:50:24"
            }
          ]
        },
        {
          "Identifier": "YBUD",
          "Distance": 185.0,
          "FlightTimes": [
            {
              "AircraftType": "JET",
              "AverageFlightTime": "00:41:10.2000000"
            },
            {
              "AircraftType": "NONJET",
              "AverageFlightTime": "00:38:24"
            }
          ]
        },
        {
          "Identifier": "YMYB",
          "Distance": 162.0,
          "FlightTimes": [
            {
              "AircraftType": "JET",
              "AverageFlightTime": "00:37:36.6000000"
            },
            {
              "AircraftType": "NONJET",
              "AverageFlightTime": "00:34:59.4000000"
            }
          ]
        },
        {
          "Identifier": "YHBA",
          "Distance": 176.0,
          "FlightTimes": [
            {
              "AircraftType": "JET",
              "AverageFlightTime": "00:39:46.8000000"
            },
            {
              "AircraftType": "NONJET",
              "AverageFlightTime": "00:37:03.6000000"
            }
          ]
        },
        {
          "Identifier": "YBSU",
          "Distance": 84.0,
          "FlightTimes": [
            {
              "AircraftType": "JET",
              "AverageFlightTime": "00:25:31.8000000"
            },
            {
              "AircraftType": "NONJET",
              "AverageFlightTime": "00:23:25.8000000"
            }
          ]
        }
      ]
    },
    {
      "Identifier": "YPPH",
      "FeederFixes": ["KAGMI", "JULIM", "KABLI", "SOLUS", "DAYLR", "LAVEX", "SAPKO"],
      "Runways": [
        { "Identifier": "03" },
        { "Identifier": "06" },
        { "Identifier": "21" },
        { "Identifier": "24" }
      ],
      "RunwayModes": [
        {
          "Identifier": "SW PLN",
          "Runways": [
            { "Identifier": "21", "LandingRateSeconds": 180 },
            { "Identifier": "24", "LandingRateSeconds": 180 }
          ]
        },
        {
          "Identifier": "NE PLN",
          "Runways": [
            { "Identifier": "03", "LandingRateSeconds": 180 }
          ]
        },
        {
          "Identifier": "06",
          "Runways": [
            { "Identifier": "06", "LandingRateSeconds": 180 }
          ]
        },
        {
          "Identifier": "21",
          "Runways": [
            { "Identifier": "21", "LandingRateSeconds": 180 }
          ]
        },
        {
          "Identifier": "24",
          "Runways": [
            { "Identifier": "24", "LandingRateSeconds": 180 }
          ]
        }
      ],
      "Arrivals": [
        {
          "FeederFix": "KAGMI",
          "ArrivalRegex": "/IPMO\\dA/",
          "Category": "Jet",
          "RunwayIntervals": {
            "03": 17,
            "06": 14,
            "21": 15,
            "24": 17
          }
        },
        {
          "FeederFix": "JULIM",
          "ArrivalRegex": "/JULI\\dA/",
          "Category": "Jet",
          "RunwayIntervals": {
            "03": 17,
            "06": 19,
            "21": 10,
            "24": 10
          }
        },
        {
          "FeederFix": "JULIM",
          "ArrivalRegex": "/JULI\\dV/",
          "Category": "Jet",
          "RunwayIntervals": {
            "03": 15,
            "06": 16
          }
        },
        {
          "FeederFix": "JULIM",
          "ArrivalRegex": "/JULI\\dX/",
          "Category": "Jet",
          "RunwayIntervals": {
            "03": 15
          }
        },
        {
          "FeederFix": "KABLI",
          "ArrivalRegex": "/KABL\\dA/",
          "Category": "Jet",
          "RunwayIntervals": {
            "03": 15,
            "06": 16,
            "21": 15,
            "24": 15
          }
        },
        {
          "FeederFix": "KABLI",
          "ArrivalRegex": "/KABL\\dV/",
          "Category": "Jet",
          "RunwayIntervals": {
            "03": 13,
            "06": 14
          }
        },
        {
          "FeederFix": "KABLI",
          "ArrivalRegex": "/KABL\\dX/",
          "Category": "Jet",
          "RunwayIntervals": {
            "03": 13
          }
        },
        {
          "FeederFix": "SOLUS",
          "ArrivalRegex": "/SOLU\\dA/",
          "Category": "Jet",
          "RunwayIntervals": {
            "03": 11,
            "06": 12,
            "21": 14,
            "24": 12
          }
        },
        {
          "FeederFix": "SOLUS",
          "ArrivalRegex": "/SOLU\\dV/",
          "Category": "Jet",
          "RunwayIntervals": {
            "03": 10,
            "06": 11
          }
        },
        {
          "FeederFix": "SOLUS",
          "ArrivalRegex": "/SOLU\\dX/",
          "Category": "Jet",
          "RunwayIntervals": {
            "03": 10
          }
        },
        {
          "FeederFix": "DAYLR",
          "ArrivalRegex": "/DAYL\\dA/",
          "AircraftType": "DH8D",
          "RunwayIntervals": {
            "03": 12,
            "06": 13
          }
        },
        {
          "FeederFix": "DAYLR",
          "ArrivalRegex": "/DAYL\\dV/",
          "AircraftType": "DH8D",
          "RunwayIntervals": {
            "03": 10,
            "06": 11
          }
        },
        {
          "FeederFix": "DAYLR",
          "ArrivalRegex": "/DAYL\\dX/",
          "AircraftType": "DH8D",
          "RunwayIntervals": {
            "03": 10
          }
        },
        {
          "FeederFix": "KAGMI",
          "ArrivalRegex": "/IPMO\\dA/",
          "AircraftType": "DH8D",
          "RunwayIntervals": {
            "03": 17,
            "06": 14,
            "21": 15,
            "24": 17
          }
        },
        {
          "FeederFix": "LAVEX",
          "ArrivalRegex": "/LAVE\\dA/",
          "AircraftType": "DH8D",
          "RunwayIntervals": {
            "03": 16,
            "06": 17,
            "21": 14,
            "24": 13
          }
        },
        {
          "FeederFix": "LAVEX",
          "ArrivalRegex": "/LAVE\\dV/",
          "AircraftType": "DH8D",
          "RunwayIntervals": {
            "03": 14,
            "06": 14
          }
        },
        {
          "FeederFix": "LAVEX",
          "ArrivalRegex": "/LAVE\\dX/",
          "AircraftType": "DH8D",
          "RunwayIntervals": {
            "03": 13
          }
        },
        {
          "FeederFix": "SAPKO",
          "ArrivalRegex": "/SAPK\\dA/",
          "AircraftType": "DH8D",
          "RunwayIntervals": {
            "03": 18,
            "06": 19,
            "21": 10,
            "24": 10
          }
        },
        {
          "FeederFix": "SAPKO",
          "ArrivalRegex": "/SAPK\\dV/",
          "AircraftType": "DH8D",
          "RunwayIntervals": {
            "03": 15,
            "06": 16
          }
        },
        {
          "FeederFix": "SAPKO",
          "ArrivalRegex": "/SAPK\\dX/",
          "AircraftType": "DH8D",
          "RunwayIntervals": {
            "03": 15
          }
        },
        {
          "FeederFix": "SOLUS",
          "ArrivalRegex": "/SOLU\\dA/",
          "AircraftType": "DH8D",
          "RunwayIntervals": {
            "03": 11,
            "06": 12,
            "21": 14,
            "24": 12
          }
        },
        {
          "FeederFix": "SOLUS",
          "ArrivalRegex": "/SOLU\\dV/",
          "AircraftType": "DH8D",
          "RunwayIntervals": {
            "03": 10,
            "06": 11
          }
        },
        {
          "FeederFix": "SOLUS",
          "ArrivalRegex": "/SOLU\\dX/",
          "AircraftType": "DH8D",
          "RunwayIntervals": {
            "03": 10
          }
        },
        {
          "FeederFix": "DAYLR",
          "ArrivalRegex": "/DAYL\\dA/",
          "Category": "NonJet",
          "RunwayIntervals": {
            "03": 13,
            "06": 15
          }
        },
        {
          "FeederFix": "DAYLR",
          "ArrivalRegex": "/DAYL\\dV/",
          "Category": "NonJet",
          "RunwayIntervals": {
            "03": 12,
            "06": 13
          }
        },
        {
          "FeederFix": "DAYLR",
          "ArrivalRegex": "/DAYL\\dX/",
          "Category": "NonJet",
          "RunwayIntervals": {
            "03": 11
          }
        },
        {
          "FeederFix": "KAGMI",
          "ArrivalRegex": "/IPMO\\dA/",
          "Category": "NonJet",
          "RunwayIntervals": {
            "03": 19,
            "06": 16,
            "21": 17,
            "24": 20
          }
        },
        {
          "FeederFix": "LAVEX",
          "ArrivalRegex": "/LAVE\\dA/",
          "Category": "NonJet",
          "RunwayIntervals": {
            "03": 18,
            "06": 20,
            "21": 16,
            "24": 15
          }
        },
        {
          "FeederFix": "LAVEX",
          "ArrivalRegex": "/LAVE\\dV/",
          "Category": "NonJet",
          "RunwayIntervals": {
            "03": 15,
            "06": 16
          }
        },
        {
          "FeederFix": "LAVEX",
          "ArrivalRegex": "/LAVE\\dX/",
          "Category": "NonJet",
          "RunwayIntervals": {
            "03": 15
          }
        },
        {
          "FeederFix": "SAPKO",
          "ArrivalRegex": "/SAPK\\dA/",
          "Category": "NonJet",
          "RunwayIntervals": {
            "03": 20,
            "06": 22,
            "21": 11,
            "24": 11
          }
        },
        {
          "FeederFix": "SAPKO",
          "ArrivalRegex": "/SAPK\\dV/",
          "Category": "NonJet",
          "RunwayIntervals": {
            "03": 17,
            "06": 18
          }
        },
        {
          "FeederFix": "SAPKO",
          "ArrivalRegex": "/SAPK\\dX/",
          "Category": "NonJet",
          "RunwayIntervals": {
            "03": 17
          }
        },

        {
          "FeederFix": "SOLUS",
          "ArrivalRegex": "/SOLU\\dA/",
          "Category": "NonJet",
          "RunwayIntervals": {
            "03": 12,
            "06": 14,
            "21": 16,
            "24": 14
          }
        },
        {
          "FeederFix": "SOLUS",
          "ArrivalRegex": "/SOLU\\dV/",
          "Category": "NonJet",
          "RunwayIntervals": {
            "03": 12,
            "06": 13
          }
        },
        {
          "FeederFix": "SOLUS",
          "ArrivalRegex": "/SOLU\\dX/",
          "Category": "NonJet",
          "RunwayIntervals": {
            "03": 11
          }
        }
      ],
      "Views": [
        {
          "Identifier": "PIY",
          "ViewMode": "Enroute",
          "TimeHorizonMinutes": 30,
          "LeftLadder": ["JULIM", "SAPKO"],
          "RightLadder": ["KABLI", "DAYLR", "LAVEX"]
        },
        {
          "Identifier": "LEA",
          "ViewMode": "Enroute",
          "TimeHorizonMinutes": 30,
          "LeftLadder": ["KAGMI"],
          "RightLadder": []
        },
        {
          "Identifier": "JAR",
          "ViewMode": "Enroute",
          "TimeHorizonMinutes": 30,
          "LeftLadder": ["SOLUS"],
          "RightLadder": []
        },
        {
          "Identifier": "ALL/HYD",
          "ViewMode": "Enroute",
          "TimeHorizonMinutes": 30,
          "LeftLadder": ["JULIM", "SAPKO", "KAGMI", "SOLUS"],
          "RightLadder": ["KABLI", "DAYLR", "LAVEX"]
        },
        {
          "Identifier": "RWY",
          "ViewMode": "Approach",
          "TimeHorizonMinutes": 45,
          "LeftLadder": ["03", "21"],
          "RightLadder": ["06", "24"]
        }
      ],
      "DepartureAirports": [
        {
          "Identifier": "YABA",
          "Distance": 230.0,
          "FlightTimes": [
            {
              "AircraftType": "JET",
              "AverageFlightTime": "00:48:08.4000000"
            },
            {
              "AircraftType": "NONJET",
              "AverageFlightTime": "00:45:03.6000000"
            }
          ]
        },
        {
          "Identifier": "YBLN",
          "Distance": 162.0,
          "FlightTimes": [
            {
              "AircraftType": "JET",
              "AverageFlightTime": "00:37:36.6000000"
            },
            {
              "AircraftType": "NONJET",
              "AverageFlightTime": "00:34:59.4000000"
            }
          ]
        },
        {
          "Identifier": "YGEL",
          "Distance": 229.0,
          "FlightTimes": [
            {
              "AircraftType": "JET",
              "AverageFlightTime": "00:47:59.4000000"
            },
            {
              "AircraftType": "NONJET",
              "AverageFlightTime": "00:44:54.6000000"
            }
          ]
        }
      ]
    }
  ],
  "CoordinationMessages": {
    "Templates": [
    "WX Dev have commenced.",
    "Standby for configuration change.",
    "Flow Planning in progress - do not use delay times until advised.",
    "Maestro delay times accurate.",
    "Contingency - No FMP.",
    "General Holding.",
    "{Callsign} MEDEVAC",
    "{Callsign} diverting",
    "{Callsign} request high speed descent"
    ]
  }
}
