<?xml version="1.0" encoding="utf-8"?>
<Maps>
  <Map Type="System" Name="CG_RWY32" Priority="1" Center="-28.164444+153.504722">
    <!--YBCG-->
    <Runway Name="14/32">
      <Threshold Name="14" Position="-28.156511+153.500706" />
      <Threshold Name="32" Position="-28.172569+153.510919" ExtendedCentrelineTrack="150.58" ExtendedCentrelineLength="10" ExtendedCentrelineTickInterval="1" />
    </Runway>
    <!--SIDs-->
    <Line>
      <!--Rwy32 APAGI5-->
      -28.156511+153.500706/
      STIMP/
      MICKS/
      CG612/
      APAGI
    </Line>
    <Line>
      <!--Rwy32 BURLI5-->
      -28.156511+153.500706/
      LUVLY/
      -28.133303+153.490651/
      -28.120869+153.494722/
      -28.111897+153.505294/
      -28.108787+153.519536/
      -28.112374+153.533633/
      -28.113516+153.535561/
      MEETA/
      MAIDS/
      BURLI/
      -28.207825+153.609787/
      -28.224802+153.614136/
      -28.242191+153.613349/
      -28.258809+153.607480/
      -28.273522+153.596926/
      -28.280819+153.588801/
      CG612
    </Line>
    <!--STARs-->
    <Line>
      <!--Rwy32 BERN1A-->
      BERNI/
      ELDUX/
      VANSU/
      ROONY/
      FIKUL
    </Line>
    <Line>
      <!--Rwy32 BERN1V-->
      FIKUL/
      JAAPI
    </Line>
    <Line>
      <!--Rwy32 LAMS1A-->
      LAMSI/
      IGLAP/
      VIDUM/
      FIKUL
    </Line>
    <Line>
      <!--Rwy32 LAMS1Y-->
      LAMSI/
      OVSOT/
      ADMAK/
      TENIP/
      ATKEN
    </Line>
    <Symbol Type="HollowTriangle">
      <Point>FIKUL</Point>
      <Point>JAAPI</Point>
      <Point>ATKEN</Point>
    </Symbol>
    <Symbol Type="HollowStar">
      <Point>STIMP</Point>
      <Point>MICKS</Point>
      <Point>CG612</Point>
      <Point>APAGI</Point>
      <Point>LUVLY</Point>
      <Point>MEETA</Point>
      <Point>MAIDS</Point>
      <Point>BURLI</Point>
      <Point>BERNI</Point>
      <Point>ELDUX</Point>
      <Point>VANSU</Point>
      <Point>ROONY</Point>
      <Point>LAMSI</Point>
      <Point>IGLAP</Point>
      <Point>VIDUM</Point>
      <Point>OVSOT</Point>
      <Point>ADMAK</Point>
      <Point>TENIP</Point>
    </Symbol>
  </Map>
  <Map Type="System" Name="CG_RWY32_NAMES" Priority="2" Center="-28.164444+153.504722">
    <Label>
      <Point>STIMP</Point>
      <Point>MICKS</Point>
      <Point>CG612</Point>
      <Point>APAGI</Point>
      <Point>LUVLY</Point>
      <Point>MEETA</Point>
      <Point>MAIDS</Point>
      <Point>BURLI</Point>
      <Point>BERNI</Point>
      <Point>ELDUX</Point>
      <Point>VANSU</Point>
      <Point>ROONY</Point>
      <Point>FIKUL</Point>
      <Point>JAAPI</Point>
      <Point>LAMSI</Point>
      <Point>IGLAP</Point>
      <Point>VIDUM</Point>
      <Point>OVSOT</Point>
      <Point>ADMAK</Point>
      <Point>TENIP</Point>
      <Point>ATKEN</Point>
      <Point>MEPEM</Point>
      <Point>GUMKI</Point>
      <Point>ROM NDB</Point>
      <Point>MIMMI</Point>
      <Point>MORRO</Point>
      <Point>WOODY</Point>
      <Point>UGTUG</Point>
      <Point>SAVER</Point>
      <Point>BONEY</Point>
      <Point>SANEG</Point>
      <Point>HUUGO</Point>
      <Point>TESSI</Point>
      <Point>ADMAR</Point>
      <Point>BANDA</Point>
      <Point>OMKAX</Point>
      <Point>SCOTT</Point>
      <Point>CHEWY</Point>
      <Point>KATEB</Point>
      <Point>ITIDE</Point>
      <Point>ISKIM</Point>
      <Point>NOLOK</Point>
      <Point>NBR NDB</Point>
      <Point>BIXAD</Point>
      <Point>GUDSO</Point>
      <Point>TAPET</Point>
      <Point>LOAFA</Point>
      <Point>GLA VOR</Point>
      <Point>BICKL</Point>
      <Point>SU VOR</Point>
      <Point>RUDEY</Point>
      <Point>MESED</Point>
      <Point>ATROP</Point>
      <Point>HARVS</Point>
      <Point>MISLY</Point>
      <Point>LAROS</Point>
      <Point>SETER</Point>
      <Point>TEBOT</Point>
      <Point>HAWKE</Point>
      <Point>COOLA</Point>
      <Point>IBUNA</Point>
      <Point>LEBIT</Point>
      <Point>ATVIL</Point>
      <Point>UNVAT</Point>
      <Point>MILTY</Point>
      <Point>SUSGI</Point>
      <Point>OTLEB</Point>
      <Point>MORBI</Point>
      <Point>REMOR</Point>
      <Point>GAYLA</Point>
      <Point>AKOBA</Point>
      <Point>SAGLI</Point>
      <Point>MAGPI</Point>
      <Point>OLDIB</Point>
      <Point>DADBO</Point>
      <Point>ALDAR</Point>
      <Point>ARM NDB</Point>
      <Point>SANAD</Point>
      <Point>TW VOR</Point>
      <Point>CFS VOR</Point>
      <Point>TUCAB</Point>
      <Point>TUCKI</Point>
      <Point>JEDDA</Point>
      <Point>DULIN</Point>
      <Point>BNA NDB</Point>
      <Point>KADSI</Point>
      <Point>UGPOT</Point>
      <Point>GAMBL</Point>
      <Point>SORTI</Point>
      <Point>RUROX</Point>
      <Point>BUD NDB</Point>
      <Point>SOSTU</Point>
      <Point>HOLIS</Point>
      <Point>RIDVO</Point>
      <Point>OK VOR</Point>
      <Point>MATVI</Point>
      <Point>DAMIN</Point>
      <Point>KANKO</Point>
      <Point>BEPNA</Point>
      <Point>YCCA</Point>
      <Point>OPIPO</Point>
      <Point>NODOR</Point>
      <Point>NIROK</Point>
      <Point>LAMUG</Point>
      <Point>SMOKA</Point>
      <Point>AGIVA</Point>
      <Point>PARRY</Point>
      <Point>ELENI</Point>
      <Point>AVGEK</Point>
      <Point>RACHL</Point>
      <Point>SUKTU</Point>
      <Point>EDPEG</Point>
      <Point>ENLIP</Point>
      <Point>SPARK</Point>
      <Point>ENAID</Point>
      <Point>YAMB</Point>
      <Point>LAGOB</Point>
      <Point>LIDPO</Point>
      <Point>PERSA</Point>
    </Label>
  </Map>
</Maps>